wheat/__init__.py
wheat/constant.py
wheat/exceptions.py
wheat/main.py
wheat/utils.py
wheat/template/Chart.yaml.template
wheat/template/Dockerfile.template
wheat/template/NOTES.txt.template
wheat/template/README.md.template
wheat/template/__init__.py
wheat/template/__init__.py.template
wheat/template/_helpers.tpl.template
wheat/template/constant.py.template
wheat/template/deployment.yaml.template
wheat/template/gitignore.template
wheat/template/gitlab-ci.yml.template
wheat/template/ingress.yaml.template
wheat/template/logging.yaml.template
wheat/template/main.py.template
wheat/template/requirements.txt.template
wheat/template/service.yaml.template
wheat/template/setup.cfg.template
wheat/template/setup.py.template
wheat/template/test.txt.template
wheat/template/test_influxdb.py.template
wheat/template/test_main_functional.py.template
wheat/template/test_main_integration.py.template
wheat/template/test_rethinkdb.py.template
wheat/template/test_service.py.template
wheat/template/test_utils.py.template
wheat/template/utils.py.template
wheat/template/values.yaml.template
chance_wheat-0.1.5.dist-info/METADATA
chance_wheat-0.1.5.dist-info/WHEEL
chance_wheat-0.1.5.dist-info/entry_points.txt
chance_wheat-0.1.5.dist-info/top_level.txt
chance_wheat-0.1.5.dist-info/RECORD
