Metadata-Version: 2.1
Name: chance-wheat
Version: 0.1.5
Summary: The python project kickstarter for chancefocus
Home-page: https://gitee.com/QianFuFinancial/wheat.git
Author: Jimin Huang
Author-email: huangjimin@whu.edu.cn
License: MIT
Platform: UNKNOWN
Requires-Dist: arrow (>=0.7.0)
Requires-Dist: mock (>=2.0.0)
Requires-Dist: nose (>=1.3.7)
Requires-Dist: coverage (>=4.1)
Requires-Dist: Sphinx (>=1.6.5)
Requires-Dist: sphinx-rtd-theme (>=0.1.9)
Requires-Dist: chance-config (>=0.0.8)
Requires-Dist: chance-kafka (>=0.0.1)
Requires-Dist: wheel (>=0.29.0)
